remote_phone_control/__init__.py
remote_phone_control/snom.py
remote_phone_control/yealink.py
remote_phone_control-0.1.0.dist-info/LICENSE
remote_phone_control-0.1.0.dist-info/METADATA
remote_phone_control-0.1.0.dist-info/WHEEL
remote_phone_control-0.1.0.dist-info/top_level.txt
remote_phone_control-0.1.0.dist-info/RECORD
