Metadata-Version: 2.1
Name: remote-phone-control
Version: 0.1.0
Summary: Remote control a SIP hardphone
Author-email: p4irin <139928764+p4irin@users.noreply.github.com>
License: MIT License
Project-URL: Homepage, https://github.com/p4irin/remote_phone_control
Project-URL: Bug Tracker, https://github.com/p4irin/remote_phone_control/issues
Keywords: sip,hardphone,snom,yealink,automation,test
Classifier: Programming Language :: Python :: 3
Classifier: Programming Language :: Python :: 3.8
Classifier: Operating System :: POSIX :: Linux
Classifier: Intended Audience :: Developers
Classifier: Intended Audience :: Telecommunications Industry
Classifier: Topic :: Communications :: Internet Phone
Classifier: Topic :: Software Development :: Libraries :: Python Modules
Classifier: Topic :: Software Development :: Quality Assurance
Classifier: Topic :: Software Development :: Testing
Classifier: License :: OSI Approved :: MIT License
Requires-Python: >=3.8.10
License-File: LICENSE
Requires-Dist: requests >=2.31.0
Provides-Extra: dev
Requires-Dist: build ==0.10.0 ; extra == 'dev'
Requires-Dist: twine >=4.0.2 ; extra == 'dev'
Requires-Dist: bumpver >=2023.1126 ; extra == 'dev'
Provides-Extra: test
Requires-Dist: python-dotenv[cli] >=1.0.0 ; extra == 'test'
